{
	"$schema": "http://schema.management.azure.com/schemas/2015-01-01/deploymentTemplate.json#",
	"contentVersion": "1.0.0.0",
	"parameters": {
		"factoryName": {
			"type": "string",
			"metadata": "Data Factory name",
			"defaultValue": "sitesh"
		}
	},
	"variables": {
		"factoryId": "[concat('Microsoft.DataFactory/factories/', parameters('factoryName'))]"
	},
	"resources": [
		{
			"name": "[concat(parameters('factoryName'), '/default')]",
			"type": "Microsoft.DataFactory/factories/globalparameters",
			"apiVersion": "2018-06-01",
			"properties": {},
			"dependsOn": []
		},
		{
			"name": "[concat(parameters('factoryName'), '/Complex_Pipeline')]",
			"type": "Microsoft.DataFactory/factories/pipelines",
			"apiVersion": "2018-06-01",
			"properties": {
				"activities": [
					{
						"name": "Web1",
						"type": "WebActivity",
						"dependsOn": [],
						"policy": {
							"timeout": "0.12:00:00",
							"retry": 0,
							"retryIntervalInSeconds": 30,
							"secureOutput": false,
							"secureInput": false
						},
						"userProperties": [],
						"typeProperties": {
							"method": "GET",
							"headers": {},
							"url": "www.google.com"
						}
					},
					{
						"name": "Web2",
						"type": "WebActivity",
						"dependsOn": [
							{
								"activity": "Web1",
								"dependencyConditions": [
									"Completed"
								]
							}
						],
						"policy": {
							"timeout": "0.12:00:00",
							"retry": 0,
							"retryIntervalInSeconds": 30,
							"secureOutput": false,
							"secureInput": false
						},
						"userProperties": [],
						"typeProperties": {
							"method": "GET",
							"headers": {},
							"url": "www.google.com"
						}
					},
					{
						"name": "Web3",
						"type": "WebActivity",
						"dependsOn": [
							{
								"activity": "Web2",
								"dependencyConditions": [
									"Completed"
								]
							}
						],
						"policy": {
							"timeout": "0.12:00:00",
							"retry": 0,
							"retryIntervalInSeconds": 30,
							"secureOutput": false,
							"secureInput": false
						},
						"userProperties": [],
						"typeProperties": {
							"method": "GET",
							"headers": {},
							"url": "www.google.com"
						}
					},
					{
						"name": "Web3_copy1",
						"type": "WebActivity",
						"dependsOn": [
							{
								"activity": "Web3",
								"dependencyConditions": [
									"Completed"
								]
							}
						],
						"policy": {
							"timeout": "0.12:00:00",
							"retry": 0,
							"retryIntervalInSeconds": 30,
							"secureOutput": false,
							"secureInput": false
						},
						"userProperties": [],
						"typeProperties": {
							"method": "GET",
							"headers": {},
							"url": "www.google.com"
						}
					},
					{
						"name": "Web3_copy1_copy1",
						"type": "WebActivity",
						"dependsOn": [
							{
								"activity": "Web3_copy1",
								"dependencyConditions": [
									"Completed"
								]
							}
						],
						"policy": {
							"timeout": "0.12:00:00",
							"retry": 0,
							"retryIntervalInSeconds": 30,
							"secureOutput": false,
							"secureInput": false
						},
						"userProperties": [],
						"typeProperties": {
							"method": "GET",
							"headers": {},
							"url": "www.google.com"
						}
					},
					{
						"name": "Web1_copy1",
						"type": "WebActivity",
						"dependsOn": [],
						"policy": {
							"timeout": "0.12:00:00",
							"retry": 0,
							"retryIntervalInSeconds": 30,
							"secureOutput": false,
							"secureInput": false
						},
						"userProperties": [],
						"typeProperties": {
							"method": "GET",
							"headers": {},
							"url": "www.google.com"
						}
					},
					{
						"name": "Web2_copy1",
						"type": "WebActivity",
						"dependsOn": [
							{
								"activity": "Web1_copy1",
								"dependencyConditions": [
									"Completed"
								]
							}
						],
						"policy": {
							"timeout": "0.12:00:00",
							"retry": 0,
							"retryIntervalInSeconds": 30,
							"secureOutput": false,
							"secureInput": false
						},
						"userProperties": [],
						"typeProperties": {
							"method": "GET",
							"headers": {},
							"url": "www.google.com"
						}
					},
					{
						"name": "Web3_copy2",
						"type": "WebActivity",
						"dependsOn": [
							{
								"activity": "Web2_copy1",
								"dependencyConditions": [
									"Completed"
								]
							}
						],
						"policy": {
							"timeout": "0.12:00:00",
							"retry": 0,
							"retryIntervalInSeconds": 30,
							"secureOutput": false,
							"secureInput": false
						},
						"userProperties": [],
						"typeProperties": {
							"method": "GET",
							"headers": {},
							"url": "www.google.com"
						}
					},
					{
						"name": "Web3_copy1_copy2",
						"type": "WebActivity",
						"dependsOn": [
							{
								"activity": "Web3_copy2",
								"dependencyConditions": [
									"Completed"
								]
							}
						],
						"policy": {
							"timeout": "0.12:00:00",
							"retry": 0,
							"retryIntervalInSeconds": 30,
							"secureOutput": false,
							"secureInput": false
						},
						"userProperties": [],
						"typeProperties": {
							"method": "GET",
							"headers": {},
							"url": "www.google.com"
						}
					},
					{
						"name": "Web3_copy1_copy1_copy1",
						"type": "WebActivity",
						"dependsOn": [
							{
								"activity": "Web3_copy1_copy2",
								"dependencyConditions": [
									"Completed"
								]
							}
						],
						"policy": {
							"timeout": "0.12:00:00",
							"retry": 0,
							"retryIntervalInSeconds": 30,
							"secureOutput": false,
							"secureInput": false
						},
						"userProperties": [],
						"typeProperties": {
							"method": "GET",
							"headers": {},
							"url": "www.google.com"
						}
					}
				],
				"policy": {
					"elapsedTimeMetric": {}
				},
				"annotations": []
			},
			"dependsOn": []
		},
		{
			"name": "[concat(parameters('factoryName'), '/Complex_Pipeline_2')]",
			"type": "Microsoft.DataFactory/factories/pipelines",
			"apiVersion": "2018-06-01",
			"properties": {
				"activities": [
					{
						"name": "Web1",
						"type": "WebActivity",
						"dependsOn": [],
						"policy": {
							"timeout": "0.12:00:00",
							"retry": 0,
							"retryIntervalInSeconds": 30,
							"secureOutput": false,
							"secureInput": false
						},
						"userProperties": [],
						"typeProperties": {
							"method": "GET",
							"headers": {},
							"url": "www.google.com"
						}
					},
					{
						"name": "Web2",
						"type": "WebActivity",
						"dependsOn": [
							{
								"activity": "Web1",
								"dependencyConditions": [
									"Completed"
								]
							}
						],
						"policy": {
							"timeout": "0.12:00:00",
							"retry": 0,
							"retryIntervalInSeconds": 30,
							"secureOutput": false,
							"secureInput": false
						},
						"userProperties": [],
						"typeProperties": {
							"method": "GET",
							"headers": {},
							"url": "www.google.com"
						}
					},
					{
						"name": "Web3",
						"type": "WebActivity",
						"dependsOn": [
							{
								"activity": "Web2",
								"dependencyConditions": [
									"Completed"
								]
							}
						],
						"policy": {
							"timeout": "0.12:00:00",
							"retry": 0,
							"retryIntervalInSeconds": 30,
							"secureOutput": false,
							"secureInput": false
						},
						"userProperties": [],
						"typeProperties": {
							"method": "GET",
							"headers": {},
							"url": "www.google.com"
						}
					},
					{
						"name": "Web3_copy1",
						"type": "WebActivity",
						"dependsOn": [
							{
								"activity": "Web3",
								"dependencyConditions": [
									"Completed"
								]
							}
						],
						"policy": {
							"timeout": "0.12:00:00",
							"retry": 0,
							"retryIntervalInSeconds": 30,
							"secureOutput": false,
							"secureInput": false
						},
						"userProperties": [],
						"typeProperties": {
							"method": "GET",
							"headers": {},
							"url": "www.google.com"
						}
					},
					{
						"name": "Web3_copy1_copy1",
						"type": "WebActivity",
						"dependsOn": [
							{
								"activity": "Web3_copy1",
								"dependencyConditions": [
									"Completed"
								]
							}
						],
						"policy": {
							"timeout": "0.12:00:00",
							"retry": 0,
							"retryIntervalInSeconds": 30,
							"secureOutput": false,
							"secureInput": false
						},
						"userProperties": [],
						"typeProperties": {
							"method": "GET",
							"headers": {},
							"url": "www.google.com"
						}
					},
					{
						"name": "Web1_copy1",
						"type": "WebActivity",
						"dependsOn": [],
						"policy": {
							"timeout": "0.12:00:00",
							"retry": 0,
							"retryIntervalInSeconds": 30,
							"secureOutput": false,
							"secureInput": false
						},
						"userProperties": [],
						"typeProperties": {
							"method": "GET",
							"headers": {},
							"url": "www.google.com"
						}
					},
					{
						"name": "Web2_copy1",
						"type": "WebActivity",
						"dependsOn": [
							{
								"activity": "Web1_copy1",
								"dependencyConditions": [
									"Completed"
								]
							}
						],
						"policy": {
							"timeout": "0.12:00:00",
							"retry": 0,
							"retryIntervalInSeconds": 30,
							"secureOutput": false,
							"secureInput": false
						},
						"userProperties": [],
						"typeProperties": {
							"method": "GET",
							"headers": {},
							"url": "www.google.com"
						}
					},
					{
						"name": "Web3_copy2",
						"type": "WebActivity",
						"dependsOn": [
							{
								"activity": "Web2_copy1",
								"dependencyConditions": [
									"Completed"
								]
							}
						],
						"policy": {
							"timeout": "0.12:00:00",
							"retry": 0,
							"retryIntervalInSeconds": 30,
							"secureOutput": false,
							"secureInput": false
						},
						"userProperties": [],
						"typeProperties": {
							"method": "GET",
							"headers": {},
							"url": "www.google.com"
						}
					},
					{
						"name": "Web3_copy1_copy2",
						"type": "WebActivity",
						"dependsOn": [
							{
								"activity": "Web3_copy2",
								"dependencyConditions": [
									"Completed"
								]
							}
						],
						"policy": {
							"timeout": "0.12:00:00",
							"retry": 0,
							"retryIntervalInSeconds": 30,
							"secureOutput": false,
							"secureInput": false
						},
						"userProperties": [],
						"typeProperties": {
							"method": "GET",
							"headers": {},
							"url": "www.google.com"
						}
					},
					{
						"name": "Web3_copy1_copy1_copy1",
						"type": "WebActivity",
						"dependsOn": [
							{
								"activity": "Web3_copy1_copy2",
								"dependencyConditions": [
									"Completed"
								]
							}
						],
						"policy": {
							"timeout": "0.12:00:00",
							"retry": 0,
							"retryIntervalInSeconds": 30,
							"secureOutput": false,
							"secureInput": false
						},
						"userProperties": [],
						"typeProperties": {
							"method": "GET",
							"headers": {},
							"url": "www.google.com"
						}
					},
					{
						"name": "Web1_copy2",
						"type": "WebActivity",
						"dependsOn": [],
						"policy": {
							"timeout": "0.12:00:00",
							"retry": 0,
							"retryIntervalInSeconds": 30,
							"secureOutput": false,
							"secureInput": false
						},
						"userProperties": [],
						"typeProperties": {
							"method": "GET",
							"headers": {},
							"url": "www.google.com"
						}
					},
					{
						"name": "Web2_copy2",
						"type": "WebActivity",
						"dependsOn": [
							{
								"activity": "Web1_copy2",
								"dependencyConditions": [
									"Completed"
								]
							}
						],
						"policy": {
							"timeout": "0.12:00:00",
							"retry": 0,
							"retryIntervalInSeconds": 30,
							"secureOutput": false,
							"secureInput": false
						},
						"userProperties": [],
						"typeProperties": {
							"method": "GET",
							"headers": {},
							"url": "www.google.com"
						}
					},
					{
						"name": "Web3_copy3",
						"type": "WebActivity",
						"dependsOn": [
							{
								"activity": "Web2_copy2",
								"dependencyConditions": [
									"Completed"
								]
							}
						],
						"policy": {
							"timeout": "0.12:00:00",
							"retry": 0,
							"retryIntervalInSeconds": 30,
							"secureOutput": false,
							"secureInput": false
						},
						"userProperties": [],
						"typeProperties": {
							"method": "GET",
							"headers": {},
							"url": "www.google.com"
						}
					},
					{
						"name": "Web3_copy1_copy3",
						"type": "WebActivity",
						"dependsOn": [
							{
								"activity": "Web3_copy3",
								"dependencyConditions": [
									"Completed"
								]
							}
						],
						"policy": {
							"timeout": "0.12:00:00",
							"retry": 0,
							"retryIntervalInSeconds": 30,
							"secureOutput": false,
							"secureInput": false
						},
						"userProperties": [],
						"typeProperties": {
							"method": "GET",
							"headers": {},
							"url": "www.google.com"
						}
					},
					{
						"name": "Web3_copy1_copy1_copy2",
						"type": "WebActivity",
						"dependsOn": [
							{
								"activity": "Web3_copy1_copy3",
								"dependencyConditions": [
									"Completed"
								]
							}
						],
						"policy": {
							"timeout": "0.12:00:00",
							"retry": 0,
							"retryIntervalInSeconds": 30,
							"secureOutput": false,
							"secureInput": false
						},
						"userProperties": [],
						"typeProperties": {
							"method": "GET",
							"headers": {},
							"url": "www.google.com"
						}
					},
					{
						"name": "Web1_copy3",
						"type": "WebActivity",
						"dependsOn": [],
						"policy": {
							"timeout": "0.12:00:00",
							"retry": 0,
							"retryIntervalInSeconds": 30,
							"secureOutput": false,
							"secureInput": false
						},
						"userProperties": [],
						"typeProperties": {
							"method": "GET",
							"headers": {},
							"url": "www.google.com"
						}
					},
					{
						"name": "Web2_copy3",
						"type": "WebActivity",
						"dependsOn": [
							{
								"activity": "Web1_copy3",
								"dependencyConditions": [
									"Completed"
								]
							}
						],
						"policy": {
							"timeout": "0.12:00:00",
							"retry": 0,
							"retryIntervalInSeconds": 30,
							"secureOutput": false,
							"secureInput": false
						},
						"userProperties": [],
						"typeProperties": {
							"method": "GET",
							"headers": {},
							"url": "www.google.com"
						}
					},
					{
						"name": "Web3_copy4",
						"type": "WebActivity",
						"dependsOn": [
							{
								"activity": "Web2_copy3",
								"dependencyConditions": [
									"Completed"
								]
							}
						],
						"policy": {
							"timeout": "0.12:00:00",
							"retry": 0,
							"retryIntervalInSeconds": 30,
							"secureOutput": false,
							"secureInput": false
						},
						"userProperties": [],
						"typeProperties": {
							"method": "GET",
							"headers": {},
							"url": "www.google.com"
						}
					},
					{
						"name": "Web3_copy1_copy4",
						"type": "WebActivity",
						"dependsOn": [
							{
								"activity": "Web3_copy4",
								"dependencyConditions": [
									"Completed"
								]
							}
						],
						"policy": {
							"timeout": "0.12:00:00",
							"retry": 0,
							"retryIntervalInSeconds": 30,
							"secureOutput": false,
							"secureInput": false
						},
						"userProperties": [],
						"typeProperties": {
							"method": "GET",
							"headers": {},
							"url": "www.google.com"
						}
					},
					{
						"name": "Web3_copy1_copy1_copy3",
						"type": "WebActivity",
						"dependsOn": [
							{
								"activity": "Web3_copy1_copy4",
								"dependencyConditions": [
									"Completed"
								]
							}
						],
						"policy": {
							"timeout": "0.12:00:00",
							"retry": 0,
							"retryIntervalInSeconds": 30,
							"secureOutput": false,
							"secureInput": false
						},
						"userProperties": [],
						"typeProperties": {
							"method": "GET",
							"headers": {},
							"url": "www.google.com"
						}
					},
					{
						"name": "Web1_copy4",
						"type": "WebActivity",
						"dependsOn": [],
						"policy": {
							"timeout": "0.12:00:00",
							"retry": 0,
							"retryIntervalInSeconds": 30,
							"secureOutput": false,
							"secureInput": false
						},
						"userProperties": [],
						"typeProperties": {
							"method": "GET",
							"headers": {},
							"url": "www.google.com"
						}
					},
					{
						"name": "Web2_copy4",
						"type": "WebActivity",
						"dependsOn": [
							{
								"activity": "Web1_copy4",
								"dependencyConditions": [
									"Completed"
								]
							}
						],
						"policy": {
							"timeout": "0.12:00:00",
							"retry": 0,
							"retryIntervalInSeconds": 30,
							"secureOutput": false,
							"secureInput": false
						},
						"userProperties": [],
						"typeProperties": {
							"method": "GET",
							"headers": {},
							"url": "www.google.com"
						}
					},
					{
						"name": "Web3_copy5",
						"type": "WebActivity",
						"dependsOn": [
							{
								"activity": "Web2_copy4",
								"dependencyConditions": [
									"Completed"
								]
							}
						],
						"policy": {
							"timeout": "0.12:00:00",
							"retry": 0,
							"retryIntervalInSeconds": 30,
							"secureOutput": false,
							"secureInput": false
						},
						"userProperties": [],
						"typeProperties": {
							"method": "GET",
							"headers": {},
							"url": "www.google.com"
						}
					},
					{
						"name": "Web3_copy1_copy5",
						"type": "WebActivity",
						"dependsOn": [
							{
								"activity": "Web3_copy5",
								"dependencyConditions": [
									"Completed"
								]
							}
						],
						"policy": {
							"timeout": "0.12:00:00",
							"retry": 0,
							"retryIntervalInSeconds": 30,
							"secureOutput": false,
							"secureInput": false
						},
						"userProperties": [],
						"typeProperties": {
							"method": "GET",
							"headers": {},
							"url": "www.google.com"
						}
					},
					{
						"name": "Web3_copy1_copy1_copy4",
						"type": "WebActivity",
						"dependsOn": [
							{
								"activity": "Web3_copy1_copy5",
								"dependencyConditions": [
									"Completed"
								]
							}
						],
						"policy": {
							"timeout": "0.12:00:00",
							"retry": 0,
							"retryIntervalInSeconds": 30,
							"secureOutput": false,
							"secureInput": false
						},
						"userProperties": [],
						"typeProperties": {
							"method": "GET",
							"headers": {},
							"url": "www.google.com"
						}
					},
					{
						"name": "Web1_copy5",
						"type": "WebActivity",
						"dependsOn": [],
						"policy": {
							"timeout": "0.12:00:00",
							"retry": 0,
							"retryIntervalInSeconds": 30,
							"secureOutput": false,
							"secureInput": false
						},
						"userProperties": [],
						"typeProperties": {
							"method": "GET",
							"headers": {},
							"url": "www.google.com"
						}
					},
					{
						"name": "Web2_copy5",
						"type": "WebActivity",
						"dependsOn": [
							{
								"activity": "Web1_copy5",
								"dependencyConditions": [
									"Completed"
								]
							}
						],
						"policy": {
							"timeout": "0.12:00:00",
							"retry": 0,
							"retryIntervalInSeconds": 30,
							"secureOutput": false,
							"secureInput": false
						},
						"userProperties": [],
						"typeProperties": {
							"method": "GET",
							"headers": {},
							"url": "www.google.com"
						}
					},
					{
						"name": "Web3_copy6",
						"type": "WebActivity",
						"dependsOn": [
							{
								"activity": "Web2_copy5",
								"dependencyConditions": [
									"Completed"
								]
							}
						],
						"policy": {
							"timeout": "0.12:00:00",
							"retry": 0,
							"retryIntervalInSeconds": 30,
							"secureOutput": false,
							"secureInput": false
						},
						"userProperties": [],
						"typeProperties": {
							"method": "GET",
							"headers": {},
							"url": "www.google.com"
						}
					},
					{
						"name": "Web3_copy1_copy6",
						"type": "WebActivity",
						"dependsOn": [
							{
								"activity": "Web3_copy6",
								"dependencyConditions": [
									"Completed"
								]
							}
						],
						"policy": {
							"timeout": "0.12:00:00",
							"retry": 0,
							"retryIntervalInSeconds": 30,
							"secureOutput": false,
							"secureInput": false
						},
						"userProperties": [],
						"typeProperties": {
							"method": "GET",
							"headers": {},
							"url": "www.google.com"
						}
					},
					{
						"name": "Web3_copy1_copy1_copy5",
						"type": "WebActivity",
						"dependsOn": [
							{
								"activity": "Web3_copy1_copy6",
								"dependencyConditions": [
									"Completed"
								]
							}
						],
						"policy": {
							"timeout": "0.12:00:00",
							"retry": 0,
							"retryIntervalInSeconds": 30,
							"secureOutput": false,
							"secureInput": false
						},
						"userProperties": [],
						"typeProperties": {
							"method": "GET",
							"headers": {},
							"url": "www.google.com"
						}
					},
					{
						"name": "Web1_copy6",
						"type": "WebActivity",
						"dependsOn": [],
						"policy": {
							"timeout": "0.12:00:00",
							"retry": 0,
							"retryIntervalInSeconds": 30,
							"secureOutput": false,
							"secureInput": false
						},
						"userProperties": [],
						"typeProperties": {
							"method": "GET",
							"headers": {},
							"url": "www.google.com"
						}
					},
					{
						"name": "Web2_copy6",
						"type": "WebActivity",
						"dependsOn": [
							{
								"activity": "Web1_copy6",
								"dependencyConditions": [
									"Completed"
								]
							}
						],
						"policy": {
							"timeout": "0.12:00:00",
							"retry": 0,
							"retryIntervalInSeconds": 30,
							"secureOutput": false,
							"secureInput": false
						},
						"userProperties": [],
						"typeProperties": {
							"method": "GET",
							"headers": {},
							"url": "www.google.com"
						}
					},
					{
						"name": "Web3_copy7",
						"type": "WebActivity",
						"dependsOn": [
							{
								"activity": "Web2_copy6",
								"dependencyConditions": [
									"Completed"
								]
							}
						],
						"policy": {
							"timeout": "0.12:00:00",
							"retry": 0,
							"retryIntervalInSeconds": 30,
							"secureOutput": false,
							"secureInput": false
						},
						"userProperties": [],
						"typeProperties": {
							"method": "GET",
							"headers": {},
							"url": "www.google.com"
						}
					},
					{
						"name": "Web3_copy1_copy7",
						"type": "WebActivity",
						"dependsOn": [
							{
								"activity": "Web3_copy7",
								"dependencyConditions": [
									"Completed"
								]
							}
						],
						"policy": {
							"timeout": "0.12:00:00",
							"retry": 0,
							"retryIntervalInSeconds": 30,
							"secureOutput": false,
							"secureInput": false
						},
						"userProperties": [],
						"typeProperties": {
							"method": "GET",
							"headers": {},
							"url": "www.google.com"
						}
					},
					{
						"name": "Web3_copy1_copy1_copy6",
						"type": "WebActivity",
						"dependsOn": [
							{
								"activity": "Web3_copy1_copy7",
								"dependencyConditions": [
									"Completed"
								]
							}
						],
						"policy": {
							"timeout": "0.12:00:00",
							"retry": 0,
							"retryIntervalInSeconds": 30,
							"secureOutput": false,
							"secureInput": false
						},
						"userProperties": [],
						"typeProperties": {
							"method": "GET",
							"headers": {},
							"url": "www.google.com"
						}
					},
					{
						"name": "Web1_copy7",
						"type": "WebActivity",
						"dependsOn": [],
						"policy": {
							"timeout": "0.12:00:00",
							"retry": 0,
							"retryIntervalInSeconds": 30,
							"secureOutput": false,
							"secureInput": false
						},
						"userProperties": [],
						"typeProperties": {
							"method": "GET",
							"headers": {},
							"url": "www.google.com"
						}
					},
					{
						"name": "Web2_copy7",
						"type": "WebActivity",
						"dependsOn": [
							{
								"activity": "Web1_copy7",
								"dependencyConditions": [
									"Completed"
								]
							}
						],
						"policy": {
							"timeout": "0.12:00:00",
							"retry": 0,
							"retryIntervalInSeconds": 30,
							"secureOutput": false,
							"secureInput": false
						},
						"userProperties": [],
						"typeProperties": {
							"method": "GET",
							"headers": {},
							"url": "www.google.com"
						}
					},
					{
						"name": "Web3_copy8",
						"type": "WebActivity",
						"dependsOn": [
							{
								"activity": "Web2_copy7",
								"dependencyConditions": [
									"Completed"
								]
							}
						],
						"policy": {
							"timeout": "0.12:00:00",
							"retry": 0,
							"retryIntervalInSeconds": 30,
							"secureOutput": false,
							"secureInput": false
						},
						"userProperties": [],
						"typeProperties": {
							"method": "GET",
							"headers": {},
							"url": "www.google.com"
						}
					},
					{
						"name": "Web3_copy1_copy8",
						"type": "WebActivity",
						"dependsOn": [
							{
								"activity": "Web3_copy8",
								"dependencyConditions": [
									"Completed"
								]
							}
						],
						"policy": {
							"timeout": "0.12:00:00",
							"retry": 0,
							"retryIntervalInSeconds": 30,
							"secureOutput": false,
							"secureInput": false
						},
						"userProperties": [],
						"typeProperties": {
							"method": "GET",
							"headers": {},
							"url": "www.google.com"
						}
					},
					{
						"name": "Web3_copy1_copy1_copy7",
						"type": "WebActivity",
						"dependsOn": [
							{
								"activity": "Web3_copy1_copy8",
								"dependencyConditions": [
									"Completed"
								]
							}
						],
						"policy": {
							"timeout": "0.12:00:00",
							"retry": 0,
							"retryIntervalInSeconds": 30,
							"secureOutput": false,
							"secureInput": false
						},
						"userProperties": [],
						"typeProperties": {
							"method": "GET",
							"headers": {},
							"url": "www.google.com"
						}
					},
					{
						"name": "Web1_copy8",
						"type": "WebActivity",
						"dependsOn": [],
						"policy": {
							"timeout": "0.12:00:00",
							"retry": 0,
							"retryIntervalInSeconds": 30,
							"secureOutput": false,
							"secureInput": false
						},
						"userProperties": [],
						"typeProperties": {
							"method": "GET",
							"headers": {},
							"url": "www.google.com"
						}
					},
					{
						"name": "Web2_copy8",
						"type": "WebActivity",
						"dependsOn": [
							{
								"activity": "Web1_copy8",
								"dependencyConditions": [
									"Completed"
								]
							}
						],
						"policy": {
							"timeout": "0.12:00:00",
							"retry": 0,
							"retryIntervalInSeconds": 30,
							"secureOutput": false,
							"secureInput": false
						},
						"userProperties": [],
						"typeProperties": {
							"method": "GET",
							"headers": {},
							"url": "www.google.com"
						}
					},
					{
						"name": "Web3_copy9",
						"type": "WebActivity",
						"dependsOn": [
							{
								"activity": "Web2_copy8",
								"dependencyConditions": [
									"Completed"
								]
							}
						],
						"policy": {
							"timeout": "0.12:00:00",
							"retry": 0,
							"retryIntervalInSeconds": 30,
							"secureOutput": false,
							"secureInput": false
						},
						"userProperties": [],
						"typeProperties": {
							"method": "GET",
							"headers": {},
							"url": "www.google.com"
						}
					},
					{
						"name": "Web3_copy1_copy9",
						"type": "WebActivity",
						"dependsOn": [
							{
								"activity": "Web3_copy9",
								"dependencyConditions": [
									"Completed"
								]
							}
						],
						"policy": {
							"timeout": "0.12:00:00",
							"retry": 0,
							"retryIntervalInSeconds": 30,
							"secureOutput": false,
							"secureInput": false
						},
						"userProperties": [],
						"typeProperties": {
							"method": "GET",
							"headers": {},
							"url": "www.google.com"
						}
					},
					{
						"name": "Web3_copy1_copy1_copy8",
						"type": "WebActivity",
						"dependsOn": [
							{
								"activity": "Web3_copy1_copy9",
								"dependencyConditions": [
									"Completed"
								]
							}
						],
						"policy": {
							"timeout": "0.12:00:00",
							"retry": 0,
							"retryIntervalInSeconds": 30,
							"secureOutput": false,
							"secureInput": false
						},
						"userProperties": [],
						"typeProperties": {
							"method": "GET",
							"headers": {},
							"url": "www.google.com"
						}
					},
					{
						"name": "Web1_copy9",
						"type": "WebActivity",
						"dependsOn": [],
						"policy": {
							"timeout": "0.12:00:00",
							"retry": 0,
							"retryIntervalInSeconds": 30,
							"secureOutput": false,
							"secureInput": false
						},
						"userProperties": [],
						"typeProperties": {
							"method": "GET",
							"headers": {},
							"url": "www.google.com"
						}
					},
					{
						"name": "Web2_copy9",
						"type": "WebActivity",
						"dependsOn": [
							{
								"activity": "Web1_copy9",
								"dependencyConditions": [
									"Completed"
								]
							}
						],
						"policy": {
							"timeout": "0.12:00:00",
							"retry": 0,
							"retryIntervalInSeconds": 30,
							"secureOutput": false,
							"secureInput": false
						},
						"userProperties": [],
						"typeProperties": {
							"method": "GET",
							"headers": {},
							"url": "www.google.com"
						}
					},
					{
						"name": "Web3_copy10",
						"type": "WebActivity",
						"dependsOn": [
							{
								"activity": "Web2_copy9",
								"dependencyConditions": [
									"Completed"
								]
							}
						],
						"policy": {
							"timeout": "0.12:00:00",
							"retry": 0,
							"retryIntervalInSeconds": 30,
							"secureOutput": false,
							"secureInput": false
						},
						"userProperties": [],
						"typeProperties": {
							"method": "GET",
							"headers": {},
							"url": "www.google.com"
						}
					},
					{
						"name": "Web3_copy1_copy10",
						"type": "WebActivity",
						"dependsOn": [
							{
								"activity": "Web3_copy10",
								"dependencyConditions": [
									"Completed"
								]
							}
						],
						"policy": {
							"timeout": "0.12:00:00",
							"retry": 0,
							"retryIntervalInSeconds": 30,
							"secureOutput": false,
							"secureInput": false
						},
						"userProperties": [],
						"typeProperties": {
							"method": "GET",
							"headers": {},
							"url": "www.google.com"
						}
					},
					{
						"name": "Web3_copy1_copy1_copy9",
						"type": "WebActivity",
						"dependsOn": [
							{
								"activity": "Web3_copy1_copy10",
								"dependencyConditions": [
									"Completed"
								]
							}
						],
						"policy": {
							"timeout": "0.12:00:00",
							"retry": 0,
							"retryIntervalInSeconds": 30,
							"secureOutput": false,
							"secureInput": false
						},
						"userProperties": [],
						"typeProperties": {
							"method": "GET",
							"headers": {},
							"url": "www.google.com"
						}
					},
					{
						"name": "Web1_copy10",
						"type": "WebActivity",
						"dependsOn": [],
						"policy": {
							"timeout": "0.12:00:00",
							"retry": 0,
							"retryIntervalInSeconds": 30,
							"secureOutput": false,
							"secureInput": false
						},
						"userProperties": [],
						"typeProperties": {
							"method": "GET",
							"headers": {},
							"url": "www.google.com"
						}
					},
					{
						"name": "Web2_copy10",
						"type": "WebActivity",
						"dependsOn": [
							{
								"activity": "Web1_copy10",
								"dependencyConditions": [
									"Completed"
								]
							}
						],
						"policy": {
							"timeout": "0.12:00:00",
							"retry": 0,
							"retryIntervalInSeconds": 30,
							"secureOutput": false,
							"secureInput": false
						},
						"userProperties": [],
						"typeProperties": {
							"method": "GET",
							"headers": {},
							"url": "www.google.com"
						}
					},
					{
						"name": "Web3_copy11",
						"type": "WebActivity",
						"dependsOn": [
							{
								"activity": "Web2_copy10",
								"dependencyConditions": [
									"Completed"
								]
							}
						],
						"policy": {
							"timeout": "0.12:00:00",
							"retry": 0,
							"retryIntervalInSeconds": 30,
							"secureOutput": false,
							"secureInput": false
						},
						"userProperties": [],
						"typeProperties": {
							"method": "GET",
							"headers": {},
							"url": "www.google.com"
						}
					},
					{
						"name": "Web3_copy1_copy11",
						"type": "WebActivity",
						"dependsOn": [
							{
								"activity": "Web3_copy11",
								"dependencyConditions": [
									"Completed"
								]
							}
						],
						"policy": {
							"timeout": "0.12:00:00",
							"retry": 0,
							"retryIntervalInSeconds": 30,
							"secureOutput": false,
							"secureInput": false
						},
						"userProperties": [],
						"typeProperties": {
							"method": "GET",
							"headers": {},
							"url": "www.google.com"
						}
					},
					{
						"name": "Web3_copy1_copy1_copy10",
						"type": "WebActivity",
						"dependsOn": [
							{
								"activity": "Web3_copy1_copy11",
								"dependencyConditions": [
									"Completed"
								]
							}
						],
						"policy": {
							"timeout": "0.12:00:00",
							"retry": 0,
							"retryIntervalInSeconds": 30,
							"secureOutput": false,
							"secureInput": false
						},
						"userProperties": [],
						"typeProperties": {
							"method": "GET",
							"headers": {},
							"url": "www.google.com"
						}
					},
					{
						"name": "Web1_copy11",
						"type": "WebActivity",
						"dependsOn": [],
						"policy": {
							"timeout": "0.12:00:00",
							"retry": 0,
							"retryIntervalInSeconds": 30,
							"secureOutput": false,
							"secureInput": false
						},
						"userProperties": [],
						"typeProperties": {
							"method": "GET",
							"headers": {},
							"url": "www.google.com"
						}
					},
					{
						"name": "Web2_copy11",
						"type": "WebActivity",
						"dependsOn": [
							{
								"activity": "Web1_copy11",
								"dependencyConditions": [
									"Completed"
								]
							}
						],
						"policy": {
							"timeout": "0.12:00:00",
							"retry": 0,
							"retryIntervalInSeconds": 30,
							"secureOutput": false,
							"secureInput": false
						},
						"userProperties": [],
						"typeProperties": {
							"method": "GET",
							"headers": {},
							"url": "www.google.com"
						}
					},
					{
						"name": "Web3_copy12",
						"type": "WebActivity",
						"dependsOn": [
							{
								"activity": "Web2_copy11",
								"dependencyConditions": [
									"Completed"
								]
							}
						],
						"policy": {
							"timeout": "0.12:00:00",
							"retry": 0,
							"retryIntervalInSeconds": 30,
							"secureOutput": false,
							"secureInput": false
						},
						"userProperties": [],
						"typeProperties": {
							"method": "GET",
							"headers": {},
							"url": "www.google.com"
						}
					},
					{
						"name": "Web3_copy1_copy12",
						"type": "WebActivity",
						"dependsOn": [
							{
								"activity": "Web3_copy12",
								"dependencyConditions": [
									"Completed"
								]
							}
						],
						"policy": {
							"timeout": "0.12:00:00",
							"retry": 0,
							"retryIntervalInSeconds": 30,
							"secureOutput": false,
							"secureInput": false
						},
						"userProperties": [],
						"typeProperties": {
							"method": "GET",
							"headers": {},
							"url": "www.google.com"
						}
					},
					{
						"name": "Web3_copy1_copy1_copy11",
						"type": "WebActivity",
						"dependsOn": [
							{
								"activity": "Web3_copy1_copy12",
								"dependencyConditions": [
									"Completed"
								]
							}
						],
						"policy": {
							"timeout": "0.12:00:00",
							"retry": 0,
							"retryIntervalInSeconds": 30,
							"secureOutput": false,
							"secureInput": false
						},
						"userProperties": [],
						"typeProperties": {
							"method": "GET",
							"headers": {},
							"url": "www.google.com"
						}
					},
					{
						"name": "Web1_copy12",
						"type": "WebActivity",
						"dependsOn": [],
						"policy": {
							"timeout": "0.12:00:00",
							"retry": 0,
							"retryIntervalInSeconds": 30,
							"secureOutput": false,
							"secureInput": false
						},
						"userProperties": [],
						"typeProperties": {
							"method": "GET",
							"headers": {},
							"url": "www.google.com"
						}
					},
					{
						"name": "Web2_copy12",
						"type": "WebActivity",
						"dependsOn": [
							{
								"activity": "Web1_copy12",
								"dependencyConditions": [
									"Completed"
								]
							}
						],
						"policy": {
							"timeout": "0.12:00:00",
							"retry": 0,
							"retryIntervalInSeconds": 30,
							"secureOutput": false,
							"secureInput": false
						},
						"userProperties": [],
						"typeProperties": {
							"method": "GET",
							"headers": {},
							"url": "www.google.com"
						}
					},
					{
						"name": "Web3_copy13",
						"type": "WebActivity",
						"dependsOn": [
							{
								"activity": "Web2_copy12",
								"dependencyConditions": [
									"Completed"
								]
							}
						],
						"policy": {
							"timeout": "0.12:00:00",
							"retry": 0,
							"retryIntervalInSeconds": 30,
							"secureOutput": false,
							"secureInput": false
						},
						"userProperties": [],
						"typeProperties": {
							"method": "GET",
							"headers": {},
							"url": "www.google.com"
						}
					},
					{
						"name": "Web3_copy1_copy13",
						"type": "WebActivity",
						"dependsOn": [
							{
								"activity": "Web3_copy13",
								"dependencyConditions": [
									"Completed"
								]
							}
						],
						"policy": {
							"timeout": "0.12:00:00",
							"retry": 0,
							"retryIntervalInSeconds": 30,
							"secureOutput": false,
							"secureInput": false
						},
						"userProperties": [],
						"typeProperties": {
							"method": "GET",
							"headers": {},
							"url": "www.google.com"
						}
					},
					{
						"name": "Web3_copy1_copy1_copy12",
						"type": "WebActivity",
						"dependsOn": [
							{
								"activity": "Web3_copy1_copy13",
								"dependencyConditions": [
									"Completed"
								]
							}
						],
						"policy": {
							"timeout": "0.12:00:00",
							"retry": 0,
							"retryIntervalInSeconds": 30,
							"secureOutput": false,
							"secureInput": false
						},
						"userProperties": [],
						"typeProperties": {
							"method": "GET",
							"headers": {},
							"url": "www.google.com"
						}
					},
					{
						"name": "Web1_copy13",
						"type": "WebActivity",
						"dependsOn": [],
						"policy": {
							"timeout": "0.12:00:00",
							"retry": 0,
							"retryIntervalInSeconds": 30,
							"secureOutput": false,
							"secureInput": false
						},
						"userProperties": [],
						"typeProperties": {
							"method": "GET",
							"headers": {},
							"url": "www.google.com"
						}
					},
					{
						"name": "Web2_copy13",
						"type": "WebActivity",
						"dependsOn": [
							{
								"activity": "Web1_copy13",
								"dependencyConditions": [
									"Completed"
								]
							}
						],
						"policy": {
							"timeout": "0.12:00:00",
							"retry": 0,
							"retryIntervalInSeconds": 30,
							"secureOutput": false,
							"secureInput": false
						},
						"userProperties": [],
						"typeProperties": {
							"method": "GET",
							"headers": {},
							"url": "www.google.com"
						}
					},
					{
						"name": "Web3_copy14",
						"type": "WebActivity",
						"dependsOn": [
							{
								"activity": "Web2_copy13",
								"dependencyConditions": [
									"Completed"
								]
							}
						],
						"policy": {
							"timeout": "0.12:00:00",
							"retry": 0,
							"retryIntervalInSeconds": 30,
							"secureOutput": false,
							"secureInput": false
						},
						"userProperties": [],
						"typeProperties": {
							"method": "GET",
							"headers": {},
							"url": "www.google.com"
						}
					},
					{
						"name": "Web3_copy1_copy14",
						"type": "WebActivity",
						"dependsOn": [
							{
								"activity": "Web3_copy14",
								"dependencyConditions": [
									"Completed"
								]
							}
						],
						"policy": {
							"timeout": "0.12:00:00",
							"retry": 0,
							"retryIntervalInSeconds": 30,
							"secureOutput": false,
							"secureInput": false
						},
						"userProperties": [],
						"typeProperties": {
							"method": "GET",
							"headers": {},
							"url": "www.google.com"
						}
					},
					{
						"name": "Web3_copy1_copy1_copy13",
						"type": "WebActivity",
						"dependsOn": [
							{
								"activity": "Web3_copy1_copy14",
								"dependencyConditions": [
									"Completed"
								]
							}
						],
						"policy": {
							"timeout": "0.12:00:00",
							"retry": 0,
							"retryIntervalInSeconds": 30,
							"secureOutput": false,
							"secureInput": false
						},
						"userProperties": [],
						"typeProperties": {
							"method": "GET",
							"headers": {},
							"url": "www.google.com"
						}
					},
					{
						"name": "Web1_copy14",
						"type": "WebActivity",
						"dependsOn": [],
						"policy": {
							"timeout": "0.12:00:00",
							"retry": 0,
							"retryIntervalInSeconds": 30,
							"secureOutput": false,
							"secureInput": false
						},
						"userProperties": [],
						"typeProperties": {
							"method": "GET",
							"headers": {},
							"url": "www.google.com"
						}
					},
					{
						"name": "Web2_copy14",
						"type": "WebActivity",
						"dependsOn": [
							{
								"activity": "Web1_copy14",
								"dependencyConditions": [
									"Completed"
								]
							}
						],
						"policy": {
							"timeout": "0.12:00:00",
							"retry": 0,
							"retryIntervalInSeconds": 30,
							"secureOutput": false,
							"secureInput": false
						},
						"userProperties": [],
						"typeProperties": {
							"method": "GET",
							"headers": {},
							"url": "www.google.com"
						}
					},
					{
						"name": "Web3_copy15",
						"type": "WebActivity",
						"dependsOn": [
							{
								"activity": "Web2_copy14",
								"dependencyConditions": [
									"Completed"
								]
							}
						],
						"policy": {
							"timeout": "0.12:00:00",
							"retry": 0,
							"retryIntervalInSeconds": 30,
							"secureOutput": false,
							"secureInput": false
						},
						"userProperties": [],
						"typeProperties": {
							"method": "GET",
							"headers": {},
							"url": "www.google.com"
						}
					},
					{
						"name": "Web3_copy1_copy15",
						"type": "WebActivity",
						"dependsOn": [
							{
								"activity": "Web3_copy15",
								"dependencyConditions": [
									"Completed"
								]
							}
						],
						"policy": {
							"timeout": "0.12:00:00",
							"retry": 0,
							"retryIntervalInSeconds": 30,
							"secureOutput": false,
							"secureInput": false
						},
						"userProperties": [],
						"typeProperties": {
							"method": "GET",
							"headers": {},
							"url": "www.google.com"
						}
					},
					{
						"name": "Web3_copy1_copy1_copy14",
						"type": "WebActivity",
						"dependsOn": [
							{
								"activity": "Web3_copy1_copy15",
								"dependencyConditions": [
									"Completed"
								]
							}
						],
						"policy": {
							"timeout": "0.12:00:00",
							"retry": 0,
							"retryIntervalInSeconds": 30,
							"secureOutput": false,
							"secureInput": false
						},
						"userProperties": [],
						"typeProperties": {
							"method": "GET",
							"headers": {},
							"url": "www.google.com"
						}
					}
				],
				"policy": {
					"elapsedTimeMetric": {}
				},
				"annotations": []
			},
			"dependsOn": []
		},
		{
			"name": "[concat(parameters('factoryName'), '/Complex_Pipeline_2_copy1')]",
			"type": "Microsoft.DataFactory/factories/pipelines",
			"apiVersion": "2018-06-01",
			"properties": {
				"activities": [
					{
						"name": "Web1",
						"type": "WebActivity",
						"dependsOn": [],
						"policy": {
							"timeout": "0.12:00:00",
							"retry": 0,
							"retryIntervalInSeconds": 30,
							"secureOutput": false,
							"secureInput": false
						},
						"userProperties": [],
						"typeProperties": {
							"method": "GET",
							"headers": {},
							"url": "www.google.com"
						}
					},
					{
						"name": "Web2",
						"type": "WebActivity",
						"dependsOn": [
							{
								"activity": "Web1",
								"dependencyConditions": [
									"Completed"
								]
							}
						],
						"policy": {
							"timeout": "0.12:00:00",
							"retry": 0,
							"retryIntervalInSeconds": 30,
							"secureOutput": false,
							"secureInput": false
						},
						"userProperties": [],
						"typeProperties": {
							"method": "GET",
							"headers": {},
							"url": "www.google.com"
						}
					},
					{
						"name": "Web3",
						"type": "WebActivity",
						"dependsOn": [
							{
								"activity": "Web2",
								"dependencyConditions": [
									"Completed"
								]
							}
						],
						"policy": {
							"timeout": "0.12:00:00",
							"retry": 0,
							"retryIntervalInSeconds": 30,
							"secureOutput": false,
							"secureInput": false
						},
						"userProperties": [],
						"typeProperties": {
							"method": "GET",
							"headers": {},
							"url": "www.google.com"
						}
					},
					{
						"name": "Web3_copy1",
						"type": "WebActivity",
						"dependsOn": [
							{
								"activity": "Web3",
								"dependencyConditions": [
									"Completed"
								]
							}
						],
						"policy": {
							"timeout": "0.12:00:00",
							"retry": 0,
							"retryIntervalInSeconds": 30,
							"secureOutput": false,
							"secureInput": false
						},
						"userProperties": [],
						"typeProperties": {
							"method": "GET",
							"headers": {},
							"url": "www.google.com"
						}
					},
					{
						"name": "Web3_copy1_copy1",
						"type": "WebActivity",
						"dependsOn": [
							{
								"activity": "Web3_copy1",
								"dependencyConditions": [
									"Completed"
								]
							}
						],
						"policy": {
							"timeout": "0.12:00:00",
							"retry": 0,
							"retryIntervalInSeconds": 30,
							"secureOutput": false,
							"secureInput": false
						},
						"userProperties": [],
						"typeProperties": {
							"method": "GET",
							"headers": {},
							"url": "www.google.com"
						}
					}
				],
				"policy": {
					"elapsedTimeMetric": {}
				},
				"annotations": []
			},
			"dependsOn": []
		},
		{
			"name": "[concat(parameters('factoryName'), '/Complex_Pipeline_2_copy2')]",
			"type": "Microsoft.DataFactory/factories/pipelines",
			"apiVersion": "2018-06-01",
			"properties": {
				"activities": [
					{
						"name": "Web1",
						"type": "WebActivity",
						"dependsOn": [],
						"policy": {
							"timeout": "0.12:00:00",
							"retry": 0,
							"retryIntervalInSeconds": 30,
							"secureOutput": false,
							"secureInput": false
						},
						"userProperties": [],
						"typeProperties": {
							"method": "GET",
							"headers": {},
							"url": "www.google.com"
						}
					},
					{
						"name": "Web2",
						"type": "WebActivity",
						"dependsOn": [
							{
								"activity": "Web1",
								"dependencyConditions": [
									"Completed"
								]
							}
						],
						"policy": {
							"timeout": "0.12:00:00",
							"retry": 0,
							"retryIntervalInSeconds": 30,
							"secureOutput": false,
							"secureInput": false
						},
						"userProperties": [],
						"typeProperties": {
							"method": "GET",
							"headers": {},
							"url": "www.google.com"
						}
					},
					{
						"name": "Web3",
						"type": "WebActivity",
						"dependsOn": [
							{
								"activity": "Web2",
								"dependencyConditions": [
									"Completed"
								]
							}
						],
						"policy": {
							"timeout": "0.12:00:00",
							"retry": 0,
							"retryIntervalInSeconds": 30,
							"secureOutput": false,
							"secureInput": false
						},
						"userProperties": [],
						"typeProperties": {
							"method": "GET",
							"headers": {},
							"url": "www.google.com"
						}
					},
					{
						"name": "Web3_copy1",
						"type": "WebActivity",
						"dependsOn": [
							{
								"activity": "Web3",
								"dependencyConditions": [
									"Completed"
								]
							}
						],
						"policy": {
							"timeout": "0.12:00:00",
							"retry": 0,
							"retryIntervalInSeconds": 30,
							"secureOutput": false,
							"secureInput": false
						},
						"userProperties": [],
						"typeProperties": {
							"method": "GET",
							"headers": {},
							"url": "www.google.com"
						}
					},
					{
						"name": "Web3_copy1_copy1",
						"type": "WebActivity",
						"dependsOn": [
							{
								"activity": "Web3_copy1",
								"dependencyConditions": [
									"Completed"
								]
							}
						],
						"policy": {
							"timeout": "0.12:00:00",
							"retry": 0,
							"retryIntervalInSeconds": 30,
							"secureOutput": false,
							"secureInput": false
						},
						"userProperties": [],
						"typeProperties": {
							"method": "GET",
							"headers": {},
							"url": "www.google.com"
						}
					}
				],
				"policy": {
					"elapsedTimeMetric": {}
				},
				"annotations": []
			},
			"dependsOn": []
		},
		{
			"name": "[concat(parameters('factoryName'), '/Complex_Pipeline_2_copy3')]",
			"type": "Microsoft.DataFactory/factories/pipelines",
			"apiVersion": "2018-06-01",
			"properties": {
				"activities": [
					{
						"name": "Web1",
						"type": "WebActivity",
						"dependsOn": [],
						"policy": {
							"timeout": "0.12:00:00",
							"retry": 0,
							"retryIntervalInSeconds": 30,
							"secureOutput": false,
							"secureInput": false
						},
						"userProperties": [],
						"typeProperties": {
							"method": "GET",
							"headers": {},
							"url": "www.google.com"
						}
					},
					{
						"name": "Web2",
						"type": "WebActivity",
						"dependsOn": [
							{
								"activity": "Web1",
								"dependencyConditions": [
									"Completed"
								]
							}
						],
						"policy": {
							"timeout": "0.12:00:00",
							"retry": 0,
							"retryIntervalInSeconds": 30,
							"secureOutput": false,
							"secureInput": false
						},
						"userProperties": [],
						"typeProperties": {
							"method": "GET",
							"headers": {},
							"url": "www.google.com"
						}
					},
					{
						"name": "Web3",
						"type": "WebActivity",
						"dependsOn": [
							{
								"activity": "Web2",
								"dependencyConditions": [
									"Completed"
								]
							}
						],
						"policy": {
							"timeout": "0.12:00:00",
							"retry": 0,
							"retryIntervalInSeconds": 30,
							"secureOutput": false,
							"secureInput": false
						},
						"userProperties": [],
						"typeProperties": {
							"method": "GET",
							"headers": {},
							"url": "www.google.com"
						}
					},
					{
						"name": "Web3_copy1",
						"type": "WebActivity",
						"dependsOn": [
							{
								"activity": "Web3",
								"dependencyConditions": [
									"Completed"
								]
							}
						],
						"policy": {
							"timeout": "0.12:00:00",
							"retry": 0,
							"retryIntervalInSeconds": 30,
							"secureOutput": false,
							"secureInput": false
						},
						"userProperties": [],
						"typeProperties": {
							"method": "GET",
							"headers": {},
							"url": "www.google.com"
						}
					},
					{
						"name": "Web3_copy1_copy1",
						"type": "WebActivity",
						"dependsOn": [
							{
								"activity": "Web3_copy1",
								"dependencyConditions": [
									"Completed"
								]
							}
						],
						"policy": {
							"timeout": "0.12:00:00",
							"retry": 0,
							"retryIntervalInSeconds": 30,
							"secureOutput": false,
							"secureInput": false
						},
						"userProperties": [],
						"typeProperties": {
							"method": "GET",
							"headers": {},
							"url": "www.google.com"
						}
					}
				],
				"policy": {
					"elapsedTimeMetric": {}
				},
				"annotations": []
			},
			"dependsOn": []
		},
		{
			"name": "[concat(parameters('factoryName'), '/Complex_Pipeline_2_copy4')]",
			"type": "Microsoft.DataFactory/factories/pipelines",
			"apiVersion": "2018-06-01",
			"properties": {
				"activities": [
					{
						"name": "Web1",
						"type": "WebActivity",
						"dependsOn": [],
						"policy": {
							"timeout": "0.12:00:00",
							"retry": 0,
							"retryIntervalInSeconds": 30,
							"secureOutput": false,
							"secureInput": false
						},
						"userProperties": [],
						"typeProperties": {
							"method": "GET",
							"headers": {},
							"url": "www.google.com"
						}
					},
					{
						"name": "Web2",
						"type": "WebActivity",
						"dependsOn": [
							{
								"activity": "Web1",
								"dependencyConditions": [
									"Completed"
								]
							}
						],
						"policy": {
							"timeout": "0.12:00:00",
							"retry": 0,
							"retryIntervalInSeconds": 30,
							"secureOutput": false,
							"secureInput": false
						},
						"userProperties": [],
						"typeProperties": {
							"method": "GET",
							"headers": {},
							"url": "www.google.com"
						}
					},
					{
						"name": "Web3",
						"type": "WebActivity",
						"dependsOn": [
							{
								"activity": "Web2",
								"dependencyConditions": [
									"Completed"
								]
							}
						],
						"policy": {
							"timeout": "0.12:00:00",
							"retry": 0,
							"retryIntervalInSeconds": 30,
							"secureOutput": false,
							"secureInput": false
						},
						"userProperties": [],
						"typeProperties": {
							"method": "GET",
							"headers": {},
							"url": "www.google.com"
						}
					},
					{
						"name": "Web3_copy1",
						"type": "WebActivity",
						"dependsOn": [
							{
								"activity": "Web3",
								"dependencyConditions": [
									"Completed"
								]
							}
						],
						"policy": {
							"timeout": "0.12:00:00",
							"retry": 0,
							"retryIntervalInSeconds": 30,
							"secureOutput": false,
							"secureInput": false
						},
						"userProperties": [],
						"typeProperties": {
							"method": "GET",
							"headers": {},
							"url": "www.google.com"
						}
					},
					{
						"name": "Web3_copy1_copy1",
						"type": "WebActivity",
						"dependsOn": [
							{
								"activity": "Web3_copy1",
								"dependencyConditions": [
									"Completed"
								]
							}
						],
						"policy": {
							"timeout": "0.12:00:00",
							"retry": 0,
							"retryIntervalInSeconds": 30,
							"secureOutput": false,
							"secureInput": false
						},
						"userProperties": [],
						"typeProperties": {
							"method": "GET",
							"headers": {},
							"url": "www.google.com"
						}
					}
				],
				"policy": {
					"elapsedTimeMetric": {}
				},
				"annotations": []
			},
			"dependsOn": []
		},
		{
			"name": "[concat(parameters('factoryName'), '/Complex_Pipeline_2_copy5')]",
			"type": "Microsoft.DataFactory/factories/pipelines",
			"apiVersion": "2018-06-01",
			"properties": {
				"activities": [
					{
						"name": "Web1",
						"type": "WebActivity",
						"dependsOn": [],
						"policy": {
							"timeout": "0.12:00:00",
							"retry": 0,
							"retryIntervalInSeconds": 30,
							"secureOutput": false,
							"secureInput": false
						},
						"userProperties": [],
						"typeProperties": {
							"method": "GET",
							"headers": {},
							"url": "www.google.com"
						}
					},
					{
						"name": "Web2",
						"type": "WebActivity",
						"dependsOn": [
							{
								"activity": "Web1",
								"dependencyConditions": [
									"Completed"
								]
							}
						],
						"policy": {
							"timeout": "0.12:00:00",
							"retry": 0,
							"retryIntervalInSeconds": 30,
							"secureOutput": false,
							"secureInput": false
						},
						"userProperties": [],
						"typeProperties": {
							"method": "GET",
							"headers": {},
							"url": "www.google.com"
						}
					},
					{
						"name": "Web3",
						"type": "WebActivity",
						"dependsOn": [
							{
								"activity": "Web2",
								"dependencyConditions": [
									"Completed"
								]
							}
						],
						"policy": {
							"timeout": "0.12:00:00",
							"retry": 0,
							"retryIntervalInSeconds": 30,
							"secureOutput": false,
							"secureInput": false
						},
						"userProperties": [],
						"typeProperties": {
							"method": "GET",
							"headers": {},
							"url": "www.google.com"
						}
					},
					{
						"name": "Web3_copy1",
						"type": "WebActivity",
						"dependsOn": [
							{
								"activity": "Web3",
								"dependencyConditions": [
									"Completed"
								]
							}
						],
						"policy": {
							"timeout": "0.12:00:00",
							"retry": 0,
							"retryIntervalInSeconds": 30,
							"secureOutput": false,
							"secureInput": false
						},
						"userProperties": [],
						"typeProperties": {
							"method": "GET",
							"headers": {},
							"url": "www.google.com"
						}
					},
					{
						"name": "Web3_copy1_copy1",
						"type": "WebActivity",
						"dependsOn": [
							{
								"activity": "Web3_copy1",
								"dependencyConditions": [
									"Completed"
								]
							}
						],
						"policy": {
							"timeout": "0.12:00:00",
							"retry": 0,
							"retryIntervalInSeconds": 30,
							"secureOutput": false,
							"secureInput": false
						},
						"userProperties": [],
						"typeProperties": {
							"method": "GET",
							"headers": {},
							"url": "www.google.com"
						}
					}
				],
				"policy": {
					"elapsedTimeMetric": {}
				},
				"annotations": []
			},
			"dependsOn": []
		},
		{
			"name": "[concat(parameters('factoryName'), '/Complex_Pipeline_2_copy6')]",
			"type": "Microsoft.DataFactory/factories/pipelines",
			"apiVersion": "2018-06-01",
			"properties": {
				"activities": [
					{
						"name": "Web1",
						"type": "WebActivity",
						"dependsOn": [],
						"policy": {
							"timeout": "0.12:00:00",
							"retry": 0,
							"retryIntervalInSeconds": 30,
							"secureOutput": false,
							"secureInput": false
						},
						"userProperties": [],
						"typeProperties": {
							"method": "GET",
							"headers": {},
							"url": "www.google.com"
						}
					},
					{
						"name": "Web2",
						"type": "WebActivity",
						"dependsOn": [
							{
								"activity": "Web1",
								"dependencyConditions": [
									"Completed"
								]
							}
						],
						"policy": {
							"timeout": "0.12:00:00",
							"retry": 0,
							"retryIntervalInSeconds": 30,
							"secureOutput": false,
							"secureInput": false
						},
						"userProperties": [],
						"typeProperties": {
							"method": "GET",
							"headers": {},
							"url": "www.google.com"
						}
					},
					{
						"name": "Web3",
						"type": "WebActivity",
						"dependsOn": [
							{
								"activity": "Web2",
								"dependencyConditions": [
									"Completed"
								]
							}
						],
						"policy": {
							"timeout": "0.12:00:00",
							"retry": 0,
							"retryIntervalInSeconds": 30,
							"secureOutput": false,
							"secureInput": false
						},
						"userProperties": [],
						"typeProperties": {
							"method": "GET",
							"headers": {},
							"url": "www.google.com"
						}
					},
					{
						"name": "Web3_copy1",
						"type": "WebActivity",
						"dependsOn": [
							{
								"activity": "Web3",
								"dependencyConditions": [
									"Completed"
								]
							}
						],
						"policy": {
							"timeout": "0.12:00:00",
							"retry": 0,
							"retryIntervalInSeconds": 30,
							"secureOutput": false,
							"secureInput": false
						},
						"userProperties": [],
						"typeProperties": {
							"method": "GET",
							"headers": {},
							"url": "www.google.com"
						}
					},
					{
						"name": "Web3_copy1_copy1",
						"type": "WebActivity",
						"dependsOn": [
							{
								"activity": "Web3_copy1",
								"dependencyConditions": [
									"Completed"
								]
							}
						],
						"policy": {
							"timeout": "0.12:00:00",
							"retry": 0,
							"retryIntervalInSeconds": 30,
							"secureOutput": false,
							"secureInput": false
						},
						"userProperties": [],
						"typeProperties": {
							"method": "GET",
							"headers": {},
							"url": "www.google.com"
						}
					}
				],
				"policy": {
					"elapsedTimeMetric": {}
				},
				"annotations": []
			},
			"dependsOn": []
		},
		{
			"name": "[concat(parameters('factoryName'), '/Complex_Pipeline_2_copy7')]",
			"type": "Microsoft.DataFactory/factories/pipelines",
			"apiVersion": "2018-06-01",
			"properties": {
				"activities": [
					{
						"name": "Web1",
						"type": "WebActivity",
						"dependsOn": [],
						"policy": {
							"timeout": "0.12:00:00",
							"retry": 0,
							"retryIntervalInSeconds": 30,
							"secureOutput": false,
							"secureInput": false
						},
						"userProperties": [],
						"typeProperties": {
							"method": "GET",
							"headers": {},
							"url": "www.google.com"
						}
					},
					{
						"name": "Web2",
						"type": "WebActivity",
						"dependsOn": [
							{
								"activity": "Web1",
								"dependencyConditions": [
									"Completed"
								]
							}
						],
						"policy": {
							"timeout": "0.12:00:00",
							"retry": 0,
							"retryIntervalInSeconds": 30,
							"secureOutput": false,
							"secureInput": false
						},
						"userProperties": [],
						"typeProperties": {
							"method": "GET",
							"headers": {},
							"url": "www.google.com"
						}
					},
					{
						"name": "Web3",
						"type": "WebActivity",
						"dependsOn": [
							{
								"activity": "Web2",
								"dependencyConditions": [
									"Completed"
								]
							}
						],
						"policy": {
							"timeout": "0.12:00:00",
							"retry": 0,
							"retryIntervalInSeconds": 30,
							"secureOutput": false,
							"secureInput": false
						},
						"userProperties": [],
						"typeProperties": {
							"method": "GET",
							"headers": {},
							"url": "www.google.com"
						}
					},
					{
						"name": "Web3_copy1",
						"type": "WebActivity",
						"dependsOn": [
							{
								"activity": "Web3",
								"dependencyConditions": [
									"Completed"
								]
							}
						],
						"policy": {
							"timeout": "0.12:00:00",
							"retry": 0,
							"retryIntervalInSeconds": 30,
							"secureOutput": false,
							"secureInput": false
						},
						"userProperties": [],
						"typeProperties": {
							"method": "GET",
							"headers": {},
							"url": "www.google.com"
						}
					},
					{
						"name": "Web3_copy1_copy1",
						"type": "WebActivity",
						"dependsOn": [
							{
								"activity": "Web3_copy1",
								"dependencyConditions": [
									"Completed"
								]
							}
						],
						"policy": {
							"timeout": "0.12:00:00",
							"retry": 0,
							"retryIntervalInSeconds": 30,
							"secureOutput": false,
							"secureInput": false
						},
						"userProperties": [],
						"typeProperties": {
							"method": "GET",
							"headers": {},
							"url": "www.google.com"
						}
					}
				],
				"policy": {
					"elapsedTimeMetric": {}
				},
				"annotations": []
			},
			"dependsOn": []
		},
		{
			"name": "[concat(parameters('factoryName'), '/Complex_Pipeline_2_copy8')]",
			"type": "Microsoft.DataFactory/factories/pipelines",
			"apiVersion": "2018-06-01",
			"properties": {
				"activities": [
					{
						"name": "Web1",
						"type": "WebActivity",
						"dependsOn": [],
						"policy": {
							"timeout": "0.12:00:00",
							"retry": 0,
							"retryIntervalInSeconds": 30,
							"secureOutput": false,
							"secureInput": false
						},
						"userProperties": [],
						"typeProperties": {
							"method": "GET",
							"headers": {},
							"url": "www.google.com"
						}
					},
					{
						"name": "Web2",
						"type": "WebActivity",
						"dependsOn": [
							{
								"activity": "Web1",
								"dependencyConditions": [
									"Completed"
								]
							}
						],
						"policy": {
							"timeout": "0.12:00:00",
							"retry": 0,
							"retryIntervalInSeconds": 30,
							"secureOutput": false,
							"secureInput": false
						},
						"userProperties": [],
						"typeProperties": {
							"method": "GET",
							"headers": {},
							"url": "www.google.com"
						}
					},
					{
						"name": "Web3",
						"type": "WebActivity",
						"dependsOn": [
							{
								"activity": "Web2",
								"dependencyConditions": [
									"Completed"
								]
							}
						],
						"policy": {
							"timeout": "0.12:00:00",
							"retry": 0,
							"retryIntervalInSeconds": 30,
							"secureOutput": false,
							"secureInput": false
						},
						"userProperties": [],
						"typeProperties": {
							"method": "GET",
							"headers": {},
							"url": "www.google.com"
						}
					},
					{
						"name": "Web3_copy1",
						"type": "WebActivity",
						"dependsOn": [
							{
								"activity": "Web3",
								"dependencyConditions": [
									"Completed"
								]
							}
						],
						"policy": {
							"timeout": "0.12:00:00",
							"retry": 0,
							"retryIntervalInSeconds": 30,
							"secureOutput": false,
							"secureInput": false
						},
						"userProperties": [],
						"typeProperties": {
							"method": "GET",
							"headers": {},
							"url": "www.google.com"
						}
					},
					{
						"name": "Web3_copy1_copy1",
						"type": "WebActivity",
						"dependsOn": [
							{
								"activity": "Web3_copy1",
								"dependencyConditions": [
									"Completed"
								]
							}
						],
						"policy": {
							"timeout": "0.12:00:00",
							"retry": 0,
							"retryIntervalInSeconds": 30,
							"secureOutput": false,
							"secureInput": false
						},
						"userProperties": [],
						"typeProperties": {
							"method": "GET",
							"headers": {},
							"url": "www.google.com"
						}
					}
				],
				"policy": {
					"elapsedTimeMetric": {}
				},
				"annotations": []
			},
			"dependsOn": []
		},
		{
			"name": "[concat(parameters('factoryName'), '/Complex_Pipeline_2_copy9')]",
			"type": "Microsoft.DataFactory/factories/pipelines",
			"apiVersion": "2018-06-01",
			"properties": {
				"activities": [
					{
						"name": "Web1",
						"type": "WebActivity",
						"dependsOn": [],
						"policy": {
							"timeout": "0.12:00:00",
							"retry": 0,
							"retryIntervalInSeconds": 30,
							"secureOutput": false,
							"secureInput": false
						},
						"userProperties": [],
						"typeProperties": {
							"method": "GET",
							"headers": {},
							"url": "www.google.com"
						}
					},
					{
						"name": "Web2",
						"type": "WebActivity",
						"dependsOn": [
							{
								"activity": "Web1",
								"dependencyConditions": [
									"Completed"
								]
							}
						],
						"policy": {
							"timeout": "0.12:00:00",
							"retry": 0,
							"retryIntervalInSeconds": 30,
							"secureOutput": false,
							"secureInput": false
						},
						"userProperties": [],
						"typeProperties": {
							"method": "GET",
							"headers": {},
							"url": "www.google.com"
						}
					},
					{
						"name": "Web3",
						"type": "WebActivity",
						"dependsOn": [
							{
								"activity": "Web2",
								"dependencyConditions": [
									"Completed"
								]
							}
						],
						"policy": {
							"timeout": "0.12:00:00",
							"retry": 0,
							"retryIntervalInSeconds": 30,
							"secureOutput": false,
							"secureInput": false
						},
						"userProperties": [],
						"typeProperties": {
							"method": "GET",
							"headers": {},
							"url": "www.google.com"
						}
					},
					{
						"name": "Web3_copy1",
						"type": "WebActivity",
						"dependsOn": [
							{
								"activity": "Web3",
								"dependencyConditions": [
									"Completed"
								]
							}
						],
						"policy": {
							"timeout": "0.12:00:00",
							"retry": 0,
							"retryIntervalInSeconds": 30,
							"secureOutput": false,
							"secureInput": false
						},
						"userProperties": [],
						"typeProperties": {
							"method": "GET",
							"headers": {},
							"url": "www.google.com"
						}
					},
					{
						"name": "Web3_copy1_copy1",
						"type": "WebActivity",
						"dependsOn": [
							{
								"activity": "Web3_copy1",
								"dependencyConditions": [
									"Completed"
								]
							}
						],
						"policy": {
							"timeout": "0.12:00:00",
							"retry": 0,
							"retryIntervalInSeconds": 30,
							"secureOutput": false,
							"secureInput": false
						},
						"userProperties": [],
						"typeProperties": {
							"method": "GET",
							"headers": {},
							"url": "www.google.com"
						}
					}
				],
				"policy": {
					"elapsedTimeMetric": {}
				},
				"annotations": []
			},
			"dependsOn": []
		},
		{
			"name": "[concat(parameters('factoryName'), '/Complex_Pipeline_2_copy10')]",
			"type": "Microsoft.DataFactory/factories/pipelines",
			"apiVersion": "2018-06-01",
			"properties": {
				"activities": [
					{
						"name": "Web1",
						"type": "WebActivity",
						"dependsOn": [],
						"policy": {
							"timeout": "0.12:00:00",
							"retry": 0,
							"retryIntervalInSeconds": 30,
							"secureOutput": false,
							"secureInput": false
						},
						"userProperties": [],
						"typeProperties": {
							"method": "GET",
							"headers": {},
							"url": "www.google.com"
						}
					},
					{
						"name": "Web2",
						"type": "WebActivity",
						"dependsOn": [
							{
								"activity": "Web1",
								"dependencyConditions": [
									"Completed"
								]
							}
						],
						"policy": {
							"timeout": "0.12:00:00",
							"retry": 0,
							"retryIntervalInSeconds": 30,
							"secureOutput": false,
							"secureInput": false
						},
						"userProperties": [],
						"typeProperties": {
							"method": "GET",
							"headers": {},
							"url": "www.google.com"
						}
					},
					{
						"name": "Web3",
						"type": "WebActivity",
						"dependsOn": [
							{
								"activity": "Web2",
								"dependencyConditions": [
									"Completed"
								]
							}
						],
						"policy": {
							"timeout": "0.12:00:00",
							"retry": 0,
							"retryIntervalInSeconds": 30,
							"secureOutput": false,
							"secureInput": false
						},
						"userProperties": [],
						"typeProperties": {
							"method": "GET",
							"headers": {},
							"url": "www.google.com"
						}
					},
					{
						"name": "Web3_copy1",
						"type": "WebActivity",
						"dependsOn": [
							{
								"activity": "Web3",
								"dependencyConditions": [
									"Completed"
								]
							}
						],
						"policy": {
							"timeout": "0.12:00:00",
							"retry": 0,
							"retryIntervalInSeconds": 30,
							"secureOutput": false,
							"secureInput": false
						},
						"userProperties": [],
						"typeProperties": {
							"method": "GET",
							"headers": {},
							"url": "www.google.com"
						}
					},
					{
						"name": "Web3_copy1_copy1",
						"type": "WebActivity",
						"dependsOn": [
							{
								"activity": "Web3_copy1",
								"dependencyConditions": [
									"Completed"
								]
							}
						],
						"policy": {
							"timeout": "0.12:00:00",
							"retry": 0,
							"retryIntervalInSeconds": 30,
							"secureOutput": false,
							"secureInput": false
						},
						"userProperties": [],
						"typeProperties": {
							"method": "GET",
							"headers": {},
							"url": "www.google.com"
						}
					}
				],
				"policy": {
					"elapsedTimeMetric": {}
				},
				"annotations": []
			},
			"dependsOn": []
		},
		{
			"name": "[concat(parameters('factoryName'), '/Complex_Pipeline_2_copy11')]",
			"type": "Microsoft.DataFactory/factories/pipelines",
			"apiVersion": "2018-06-01",
			"properties": {
				"activities": [
					{
						"name": "Web1",
						"type": "WebActivity",
						"dependsOn": [],
						"policy": {
							"timeout": "0.12:00:00",
							"retry": 0,
							"retryIntervalInSeconds": 30,
							"secureOutput": false,
							"secureInput": false
						},
						"userProperties": [],
						"typeProperties": {
							"method": "GET",
							"headers": {},
							"url": "www.google.com"
						}
					},
					{
						"name": "Web2",
						"type": "WebActivity",
						"dependsOn": [
							{
								"activity": "Web1",
								"dependencyConditions": [
									"Completed"
								]
							}
						],
						"policy": {
							"timeout": "0.12:00:00",
							"retry": 0,
							"retryIntervalInSeconds": 30,
							"secureOutput": false,
							"secureInput": false
						},
						"userProperties": [],
						"typeProperties": {
							"method": "GET",
							"headers": {},
							"url": "www.google.com"
						}
					},
					{
						"name": "Web3",
						"type": "WebActivity",
						"dependsOn": [
							{
								"activity": "Web2",
								"dependencyConditions": [
									"Completed"
								]
							}
						],
						"policy": {
							"timeout": "0.12:00:00",
							"retry": 0,
							"retryIntervalInSeconds": 30,
							"secureOutput": false,
							"secureInput": false
						},
						"userProperties": [],
						"typeProperties": {
							"method": "GET",
							"headers": {},
							"url": "www.google.com"
						}
					},
					{
						"name": "Web3_copy1",
						"type": "WebActivity",
						"dependsOn": [
							{
								"activity": "Web3",
								"dependencyConditions": [
									"Completed"
								]
							}
						],
						"policy": {
							"timeout": "0.12:00:00",
							"retry": 0,
							"retryIntervalInSeconds": 30,
							"secureOutput": false,
							"secureInput": false
						},
						"userProperties": [],
						"typeProperties": {
							"method": "GET",
							"headers": {},
							"url": "www.google.com"
						}
					},
					{
						"name": "Web3_copy1_copy1",
						"type": "WebActivity",
						"dependsOn": [
							{
								"activity": "Web3_copy1",
								"dependencyConditions": [
									"Completed"
								]
							}
						],
						"policy": {
							"timeout": "0.12:00:00",
							"retry": 0,
							"retryIntervalInSeconds": 30,
							"secureOutput": false,
							"secureInput": false
						},
						"userProperties": [],
						"typeProperties": {
							"method": "GET",
							"headers": {},
							"url": "www.google.com"
						}
					}
				],
				"policy": {
					"elapsedTimeMetric": {}
				},
				"annotations": []
			},
			"dependsOn": []
		},
		{
			"name": "[concat(parameters('factoryName'), '/Complex_Pipeline_2_copy12')]",
			"type": "Microsoft.DataFactory/factories/pipelines",
			"apiVersion": "2018-06-01",
			"properties": {
				"activities": [
					{
						"name": "Web1",
						"type": "WebActivity",
						"dependsOn": [],
						"policy": {
							"timeout": "0.12:00:00",
							"retry": 0,
							"retryIntervalInSeconds": 30,
							"secureOutput": false,
							"secureInput": false
						},
						"userProperties": [],
						"typeProperties": {
							"method": "GET",
							"headers": {},
							"url": "www.google.com"
						}
					},
					{
						"name": "Web2",
						"type": "WebActivity",
						"dependsOn": [
							{
								"activity": "Web1",
								"dependencyConditions": [
									"Completed"
								]
							}
						],
						"policy": {
							"timeout": "0.12:00:00",
							"retry": 0,
							"retryIntervalInSeconds": 30,
							"secureOutput": false,
							"secureInput": false
						},
						"userProperties": [],
						"typeProperties": {
							"method": "GET",
							"headers": {},
							"url": "www.google.com"
						}
					},
					{
						"name": "Web3",
						"type": "WebActivity",
						"dependsOn": [
							{
								"activity": "Web2",
								"dependencyConditions": [
									"Completed"
								]
							}
						],
						"policy": {
							"timeout": "0.12:00:00",
							"retry": 0,
							"retryIntervalInSeconds": 30,
							"secureOutput": false,
							"secureInput": false
						},
						"userProperties": [],
						"typeProperties": {
							"method": "GET",
							"headers": {},
							"url": "www.google.com"
						}
					},
					{
						"name": "Web3_copy1",
						"type": "WebActivity",
						"dependsOn": [
							{
								"activity": "Web3",
								"dependencyConditions": [
									"Completed"
								]
							}
						],
						"policy": {
							"timeout": "0.12:00:00",
							"retry": 0,
							"retryIntervalInSeconds": 30,
							"secureOutput": false,
							"secureInput": false
						},
						"userProperties": [],
						"typeProperties": {
							"method": "GET",
							"headers": {},
							"url": "www.google.com"
						}
					},
					{
						"name": "Web3_copy1_copy1",
						"type": "WebActivity",
						"dependsOn": [
							{
								"activity": "Web3_copy1",
								"dependencyConditions": [
									"Completed"
								]
							}
						],
						"policy": {
							"timeout": "0.12:00:00",
							"retry": 0,
							"retryIntervalInSeconds": 30,
							"secureOutput": false,
							"secureInput": false
						},
						"userProperties": [],
						"typeProperties": {
							"method": "GET",
							"headers": {},
							"url": "www.google.com"
						}
					}
				],
				"policy": {
					"elapsedTimeMetric": {}
				},
				"annotations": []
			},
			"dependsOn": []
		},
		{
			"name": "[concat(parameters('factoryName'), '/Complex_Pipeline_2_copy13')]",
			"type": "Microsoft.DataFactory/factories/pipelines",
			"apiVersion": "2018-06-01",
			"properties": {
				"activities": [
					{
						"name": "Web1",
						"type": "WebActivity",
						"dependsOn": [],
						"policy": {
							"timeout": "0.12:00:00",
							"retry": 0,
							"retryIntervalInSeconds": 30,
							"secureOutput": false,
							"secureInput": false
						},
						"userProperties": [],
						"typeProperties": {
							"method": "GET",
							"headers": {},
							"url": "www.google.com"
						}
					},
					{
						"name": "Web2",
						"type": "WebActivity",
						"dependsOn": [
							{
								"activity": "Web1",
								"dependencyConditions": [
									"Completed"
								]
							}
						],
						"policy": {
							"timeout": "0.12:00:00",
							"retry": 0,
							"retryIntervalInSeconds": 30,
							"secureOutput": false,
							"secureInput": false
						},
						"userProperties": [],
						"typeProperties": {
							"method": "GET",
							"headers": {},
							"url": "www.google.com"
						}
					},
					{
						"name": "Web3",
						"type": "WebActivity",
						"dependsOn": [
							{
								"activity": "Web2",
								"dependencyConditions": [
									"Completed"
								]
							}
						],
						"policy": {
							"timeout": "0.12:00:00",
							"retry": 0,
							"retryIntervalInSeconds": 30,
							"secureOutput": false,
							"secureInput": false
						},
						"userProperties": [],
						"typeProperties": {
							"method": "GET",
							"headers": {},
							"url": "www.google.com"
						}
					},
					{
						"name": "Web3_copy1",
						"type": "WebActivity",
						"dependsOn": [
							{
								"activity": "Web3",
								"dependencyConditions": [
									"Completed"
								]
							}
						],
						"policy": {
							"timeout": "0.12:00:00",
							"retry": 0,
							"retryIntervalInSeconds": 30,
							"secureOutput": false,
							"secureInput": false
						},
						"userProperties": [],
						"typeProperties": {
							"method": "GET",
							"headers": {},
							"url": "www.google.com"
						}
					},
					{
						"name": "Web3_copy1_copy1",
						"type": "WebActivity",
						"dependsOn": [
							{
								"activity": "Web3_copy1",
								"dependencyConditions": [
									"Completed"
								]
							}
						],
						"policy": {
							"timeout": "0.12:00:00",
							"retry": 0,
							"retryIntervalInSeconds": 30,
							"secureOutput": false,
							"secureInput": false
						},
						"userProperties": [],
						"typeProperties": {
							"method": "GET",
							"headers": {},
							"url": "www.google.com"
						}
					}
				],
				"policy": {
					"elapsedTimeMetric": {}
				},
				"annotations": []
			},
			"dependsOn": []
		},
		{
			"name": "[concat(parameters('factoryName'), '/Complex_Pipeline_2_copy14')]",
			"type": "Microsoft.DataFactory/factories/pipelines",
			"apiVersion": "2018-06-01",
			"properties": {
				"activities": [
					{
						"name": "Web1",
						"type": "WebActivity",
						"dependsOn": [],
						"policy": {
							"timeout": "0.12:00:00",
							"retry": 0,
							"retryIntervalInSeconds": 30,
							"secureOutput": false,
							"secureInput": false
						},
						"userProperties": [],
						"typeProperties": {
							"method": "GET",
							"headers": {},
							"url": "www.google.com"
						}
					},
					{
						"name": "Web2",
						"type": "WebActivity",
						"dependsOn": [
							{
								"activity": "Web1",
								"dependencyConditions": [
									"Completed"
								]
							}
						],
						"policy": {
							"timeout": "0.12:00:00",
							"retry": 0,
							"retryIntervalInSeconds": 30,
							"secureOutput": false,
							"secureInput": false
						},
						"userProperties": [],
						"typeProperties": {
							"method": "GET",
							"headers": {},
							"url": "www.google.com"
						}
					},
					{
						"name": "Web3",
						"type": "WebActivity",
						"dependsOn": [
							{
								"activity": "Web2",
								"dependencyConditions": [
									"Completed"
								]
							}
						],
						"policy": {
							"timeout": "0.12:00:00",
							"retry": 0,
							"retryIntervalInSeconds": 30,
							"secureOutput": false,
							"secureInput": false
						},
						"userProperties": [],
						"typeProperties": {
							"method": "GET",
							"headers": {},
							"url": "www.google.com"
						}
					},
					{
						"name": "Web3_copy1",
						"type": "WebActivity",
						"dependsOn": [
							{
								"activity": "Web3",
								"dependencyConditions": [
									"Completed"
								]
							}
						],
						"policy": {
							"timeout": "0.12:00:00",
							"retry": 0,
							"retryIntervalInSeconds": 30,
							"secureOutput": false,
							"secureInput": false
						},
						"userProperties": [],
						"typeProperties": {
							"method": "GET",
							"headers": {},
							"url": "www.google.com"
						}
					},
					{
						"name": "Web3_copy1_copy1",
						"type": "WebActivity",
						"dependsOn": [
							{
								"activity": "Web3_copy1",
								"dependencyConditions": [
									"Completed"
								]
							}
						],
						"policy": {
							"timeout": "0.12:00:00",
							"retry": 0,
							"retryIntervalInSeconds": 30,
							"secureOutput": false,
							"secureInput": false
						},
						"userProperties": [],
						"typeProperties": {
							"method": "GET",
							"headers": {},
							"url": "www.google.com"
						}
					}
				],
				"policy": {
					"elapsedTimeMetric": {}
				},
				"annotations": []
			},
			"dependsOn": []
		},
		{
			"name": "[concat(parameters('factoryName'), '/Complex_Pipeline_2_copy15')]",
			"type": "Microsoft.DataFactory/factories/pipelines",
			"apiVersion": "2018-06-01",
			"properties": {
				"activities": [
					{
						"name": "Web1",
						"type": "WebActivity",
						"dependsOn": [],
						"policy": {
							"timeout": "0.12:00:00",
							"retry": 0,
							"retryIntervalInSeconds": 30,
							"secureOutput": false,
							"secureInput": false
						},
						"userProperties": [],
						"typeProperties": {
							"method": "GET",
							"headers": {},
							"url": "www.google.com"
						}
					},
					{
						"name": "Web2",
						"type": "WebActivity",
						"dependsOn": [
							{
								"activity": "Web1",
								"dependencyConditions": [
									"Completed"
								]
							}
						],
						"policy": {
							"timeout": "0.12:00:00",
							"retry": 0,
							"retryIntervalInSeconds": 30,
							"secureOutput": false,
							"secureInput": false
						},
						"userProperties": [],
						"typeProperties": {
							"method": "GET",
							"headers": {},
							"url": "www.google.com"
						}
					},
					{
						"name": "Web3",
						"type": "WebActivity",
						"dependsOn": [
							{
								"activity": "Web2",
								"dependencyConditions": [
									"Completed"
								]
							}
						],
						"policy": {
							"timeout": "0.12:00:00",
							"retry": 0,
							"retryIntervalInSeconds": 30,
							"secureOutput": false,
							"secureInput": false
						},
						"userProperties": [],
						"typeProperties": {
							"method": "GET",
							"headers": {},
							"url": "www.google.com"
						}
					},
					{
						"name": "Web3_copy1",
						"type": "WebActivity",
						"dependsOn": [
							{
								"activity": "Web3",
								"dependencyConditions": [
									"Completed"
								]
							}
						],
						"policy": {
							"timeout": "0.12:00:00",
							"retry": 0,
							"retryIntervalInSeconds": 30,
							"secureOutput": false,
							"secureInput": false
						},
						"userProperties": [],
						"typeProperties": {
							"method": "GET",
							"headers": {},
							"url": "www.google.com"
						}
					},
					{
						"name": "Web3_copy1_copy1",
						"type": "WebActivity",
						"dependsOn": [
							{
								"activity": "Web3_copy1",
								"dependencyConditions": [
									"Completed"
								]
							}
						],
						"policy": {
							"timeout": "0.12:00:00",
							"retry": 0,
							"retryIntervalInSeconds": 30,
							"secureOutput": false,
							"secureInput": false
						},
						"userProperties": [],
						"typeProperties": {
							"method": "GET",
							"headers": {},
							"url": "www.google.com"
						}
					}
				],
				"policy": {
					"elapsedTimeMetric": {}
				},
				"annotations": []
			},
			"dependsOn": []
		},
		{
			"name": "[concat(parameters('factoryName'), '/Complex_Pipeline_2_copy16')]",
			"type": "Microsoft.DataFactory/factories/pipelines",
			"apiVersion": "2018-06-01",
			"properties": {
				"activities": [
					{
						"name": "Web1",
						"type": "WebActivity",
						"dependsOn": [],
						"policy": {
							"timeout": "0.12:00:00",
							"retry": 0,
							"retryIntervalInSeconds": 30,
							"secureOutput": false,
							"secureInput": false
						},
						"userProperties": [],
						"typeProperties": {
							"method": "GET",
							"headers": {},
							"url": "www.google.com"
						}
					},
					{
						"name": "Web2",
						"type": "WebActivity",
						"dependsOn": [
							{
								"activity": "Web1",
								"dependencyConditions": [
									"Completed"
								]
							}
						],
						"policy": {
							"timeout": "0.12:00:00",
							"retry": 0,
							"retryIntervalInSeconds": 30,
							"secureOutput": false,
							"secureInput": false
						},
						"userProperties": [],
						"typeProperties": {
							"method": "GET",
							"headers": {},
							"url": "www.google.com"
						}
					},
					{
						"name": "Web3",
						"type": "WebActivity",
						"dependsOn": [
							{
								"activity": "Web2",
								"dependencyConditions": [
									"Completed"
								]
							}
						],
						"policy": {
							"timeout": "0.12:00:00",
							"retry": 0,
							"retryIntervalInSeconds": 30,
							"secureOutput": false,
							"secureInput": false
						},
						"userProperties": [],
						"typeProperties": {
							"method": "GET",
							"headers": {},
							"url": "www.google.com"
						}
					},
					{
						"name": "Web3_copy1",
						"type": "WebActivity",
						"dependsOn": [
							{
								"activity": "Web3",
								"dependencyConditions": [
									"Completed"
								]
							}
						],
						"policy": {
							"timeout": "0.12:00:00",
							"retry": 0,
							"retryIntervalInSeconds": 30,
							"secureOutput": false,
							"secureInput": false
						},
						"userProperties": [],
						"typeProperties": {
							"method": "GET",
							"headers": {},
							"url": "www.google.com"
						}
					},
					{
						"name": "Web3_copy1_copy1",
						"type": "WebActivity",
						"dependsOn": [
							{
								"activity": "Web3_copy1",
								"dependencyConditions": [
									"Completed"
								]
							}
						],
						"policy": {
							"timeout": "0.12:00:00",
							"retry": 0,
							"retryIntervalInSeconds": 30,
							"secureOutput": false,
							"secureInput": false
						},
						"userProperties": [],
						"typeProperties": {
							"method": "GET",
							"headers": {},
							"url": "www.google.com"
						}
					}
				],
				"policy": {
					"elapsedTimeMetric": {}
				},
				"annotations": []
			},
			"dependsOn": []
		},
		{
			"name": "[concat(parameters('factoryName'), '/Complex_Pipeline_2_copy17')]",
			"type": "Microsoft.DataFactory/factories/pipelines",
			"apiVersion": "2018-06-01",
			"properties": {
				"activities": [
					{
						"name": "Web1",
						"type": "WebActivity",
						"dependsOn": [],
						"policy": {
							"timeout": "0.12:00:00",
							"retry": 0,
							"retryIntervalInSeconds": 30,
							"secureOutput": false,
							"secureInput": false
						},
						"userProperties": [],
						"typeProperties": {
							"method": "GET",
							"headers": {},
							"url": "www.google.com"
						}
					},
					{
						"name": "Web2",
						"type": "WebActivity",
						"dependsOn": [
							{
								"activity": "Web1",
								"dependencyConditions": [
									"Completed"
								]
							}
						],
						"policy": {
							"timeout": "0.12:00:00",
							"retry": 0,
							"retryIntervalInSeconds": 30,
							"secureOutput": false,
							"secureInput": false
						},
						"userProperties": [],
						"typeProperties": {
							"method": "GET",
							"headers": {},
							"url": "www.google.com"
						}
					},
					{
						"name": "Web3",
						"type": "WebActivity",
						"dependsOn": [
							{
								"activity": "Web2",
								"dependencyConditions": [
									"Completed"
								]
							}
						],
						"policy": {
							"timeout": "0.12:00:00",
							"retry": 0,
							"retryIntervalInSeconds": 30,
							"secureOutput": false,
							"secureInput": false
						},
						"userProperties": [],
						"typeProperties": {
							"method": "GET",
							"headers": {},
							"url": "www.google.com"
						}
					},
					{
						"name": "Web3_copy1",
						"type": "WebActivity",
						"dependsOn": [
							{
								"activity": "Web3",
								"dependencyConditions": [
									"Completed"
								]
							}
						],
						"policy": {
							"timeout": "0.12:00:00",
							"retry": 0,
							"retryIntervalInSeconds": 30,
							"secureOutput": false,
							"secureInput": false
						},
						"userProperties": [],
						"typeProperties": {
							"method": "GET",
							"headers": {},
							"url": "www.google.com"
						}
					},
					{
						"name": "Web3_copy1_copy1",
						"type": "WebActivity",
						"dependsOn": [
							{
								"activity": "Web3_copy1",
								"dependencyConditions": [
									"Completed"
								]
							}
						],
						"policy": {
							"timeout": "0.12:00:00",
							"retry": 0,
							"retryIntervalInSeconds": 30,
							"secureOutput": false,
							"secureInput": false
						},
						"userProperties": [],
						"typeProperties": {
							"method": "GET",
							"headers": {},
							"url": "www.google.com"
						}
					}
				],
				"policy": {
					"elapsedTimeMetric": {}
				},
				"annotations": []
			},
			"dependsOn": []
		}
	]
}